dls_ldap_query/__init__.py
dls_ldap_query/__main__.py
dls_ldap_query/_version.py
dls_ldap_query/formatter.py
dls_ldap_query/github.py
dls_ldap_query/ldap.py
dls_ldap_query-0.5.1.dist-info/licenses/LICENSE
dls_ldap_query-0.5.1.dist-info/METADATA
dls_ldap_query-0.5.1.dist-info/WHEEL
dls_ldap_query-0.5.1.dist-info/entry_points.txt
dls_ldap_query-0.5.1.dist-info/top_level.txt
dls_ldap_query-0.5.1.dist-info/RECORD
