Metadata-Version: 2.4
Name: dls-ldap-query
Version: 0.5.1
Summary: Format lists of users by querying LDAP
Author-email: Giles Knap <giles.knap@diamond.ac.uk>
License:                                  Apache License
Project-URL: GitHub, https://github.com/DiamondLightSource/dls-ldap-query
Classifier: Development Status :: 3 - Alpha
Classifier: License :: OSI Approved :: Apache Software License
Classifier: Programming Language :: Python :: 3.11
Classifier: Programming Language :: Python :: 3.12
Classifier: Programming Language :: Python :: 3.13
Requires-Python: >=3.10
License-File: LICENSE
Requires-Dist: ldap3
Requires-Dist: typer
Provides-Extra: dev
Requires-Dist: copier; extra == "dev"
Requires-Dist: pipdeptree; extra == "dev"
Requires-Dist: pre-commit; extra == "dev"
Requires-Dist: pyright; extra == "dev"
Requires-Dist: pytest; extra == "dev"
Requires-Dist: pytest-cov; extra == "dev"
Requires-Dist: ruff; extra == "dev"
Requires-Dist: tox-direct; extra == "dev"
Requires-Dist: types-mock; extra == "dev"
Dynamic: license-file
